Metadata-Version: 2.1
Name: sheet-df
Version: 0.0.1
Summary: Google sheet to dataframe
Home-page: https://github.com/neo-andrew-moss/sheet_df
Author: Andrew Moss
Author-email: andrew.moss@neofinancial.com
License: MIT license
Keywords: sheet_df
Platform: UNKNOWN
Classifier: Development Status :: 2 - Pre-Alpha
Classifier: Intended Audience :: Developers
Classifier: License :: OSI Approved :: MIT License
Classifier: Natural Language :: English
Classifier: Programming Language :: Python :: 3
Classifier: Programming Language :: Python :: 3.6
Classifier: Programming Language :: Python :: 3.7
Classifier: Programming Language :: Python :: 3.8
Requires-Python: >=3.6
License-File: LICENSE
